Metadata-Version: 1.1
Name: simple-blockchain
Version: 0.1.1
Summary: This is a simplified model of a blockchain, which is also the technology behind the well known crypto-currency Bitcoin.
Home-page: https://github.com/alekssadowski95/simple-blockchain
Author: Aleksander Sadowski
Author-email: aleksander.sadowski@alsado.de
License: MIT License
